[
  {
    "author": "Павел Федотов",
    "name": "Сватовство майора",
    "year": "1852",
    "imageNum": "0"
  },
  {
    "author": "Эдгар Дега",
    "name": "Голубые танцовщицы",
    "year": "1897",
    "imageNum": "1"
  },
  {
    "author": "Веронезе",
    "name": "Пир в доме Левия",
    "year": "1563",
    "imageNum": "2"
  },
  {
    "author": "Илья Репин",
    "name": "Иван Грозный и сын его Иван",
    "year": "1885",
    "imageNum": "3"
  },
  {
    "author": "Константин Маковский",
    "name": "Портрет графини Софьи",
    "year": "1890",
    "imageNum": "4"
  },
  {
    "author": "Василий Перов",
    "name": "Приезд гувернантки в купеческий дом",
    "year": "1866",
    "imageNum": "5"
  },
  {
    "author": "Микеланджело",
    "name": "Сотворение Адама",
    "year": "1511",
    "imageNum": "6"
  },
  {
    "author": "Пьер Огюст Ренуар",
    "name": "Прогулка в Булонском лесу",
    "year": "1873",
    "imageNum": "7"
  },
  {
    "author": "Ян Вермеер",
    "name": "Хозяйка и служанка",
    "year": "1667",
    "imageNum": "8"
  },
  {
    "author": "Василий Поленов",
    "name": "Московский дворик",
    "year": "1877",
    "imageNum": "9"
  }
]